Metadata-Version: 1.0
Name: colubridae
Version: 0.0.2
Summary: Applied Category Theory in Python
Home-page: https://github.com/AlexPof/colubridae.git
Author: Alexandre Popoff
Author-email: al.popoff@free.fr
License: BSD-3
Platform: UNKNOWN
